gmail2json.py
gmail2json-2.5.dist-info/METADATA
gmail2json-2.5.dist-info/WHEEL
gmail2json-2.5.dist-info/top_level.txt
gmail2json-2.5.dist-info/RECORD
