Metadata-Version: 2.1
Name: gmail2json
Version: 2.5
Summary: UNKNOWN
Home-page: UNKNOWN
Author: Hudge
Author-email: 
License: UNKNOWN
Platform: UNKNOWN
Classifier: Programming Language :: Python :: 3
Classifier: License :: OSI Approved :: MIT License
Classifier: Operating System :: OS Independent
Requires-Dist: google-api-python-client
Requires-Dist: google-auth-httplib2
Requires-Dist: google-auth-oauthlib
Requires-Dist: google-auth
Requires-Dist: mail-parser
